cofcokoai/__init__.py
cofcokoai-2024.0.1.1.dist-info/LICENSE
cofcokoai-2024.0.1.1.dist-info/METADATA
cofcokoai-2024.0.1.1.dist-info/WHEEL
cofcokoai-2024.0.1.1.dist-info/RECORD
